vsts/__init__.py
vsts/cli/__init__.py
vsts/cli/__main__.py
vsts/cli/vsts_cli.py
vsts/cli/vsts_cli_help.py
vsts/cli/vsts_commands_loader.py
vsts/tests/__init__.py
vsts/tests/test_vsts_cli.py
vsts_cli-0.1.4.dist-info/LICENSE.txt
vsts_cli-0.1.4.dist-info/METADATA
vsts_cli-0.1.4.dist-info/WHEEL
vsts_cli-0.1.4.dist-info/entry_points.txt
vsts_cli-0.1.4.dist-info/top_level.txt
vsts_cli-0.1.4.dist-info/RECORD
