Metadata-Version: 2.1
Name: vsts-cli
Version: 0.1.4
Summary: VSTS Command Line Interface
Home-page: https://github.com/Microsoft/vsts-cli
Author: Microsoft Corporation
Author-email: vstscli@microsoft.com
License: MIT
Keywords: Microsoft,VSTS,Team Services,SDK,AzureTfs,CLI
Platform: UNKNOWN
Classifier: Development Status :: 4 - Beta
Classifier: Intended Audience :: Developers
Classifier: Intended Audience :: System Administrators
Classifier: Programming Language :: Python
Classifier: Programming Language :: Python :: 2
Classifier: Programming Language :: Python :: 2.7
Classifier: Programming Language :: Python :: 3
Classifier: Programming Language :: Python :: 3.6
Classifier: License :: OSI Approved :: MIT License
Requires-Dist: knack (==0.4.1)
Requires-Dist: setuptools
Requires-Dist: vsts-cli-common (==0.1.4)
Requires-Dist: vsts-cli-admin (==0.1.4)
Requires-Dist: vsts-cli-build (==0.1.4)
Requires-Dist: vsts-cli-release (==0.1.4)
Requires-Dist: vsts-cli-code (==0.1.4)
Requires-Dist: vsts-cli-team (==0.1.4)
Requires-Dist: vsts-cli-package (==0.1.4)
Requires-Dist: vsts-cli-work (==0.1.4)
